moransi/__init__.py
moransi/_moransi.py
moransi/_tests/__init__.py
moransi/_tests/test_moransi.py
moransi-1.0.1.dist-info/licenses/LICENSE
moransi-1.0.1.dist-info/METADATA
moransi-1.0.1.dist-info/WHEEL
moransi-1.0.1.dist-info/top_level.txt
moransi-1.0.1.dist-info/RECORD
