Metadata-Version: 2.4
Name: moransi
Version: 1.0.1
Summary: Compute Moran's Index for images or adjacency matrix
Author-email: Leo Guignard <leo.guignard@univ-amu.fr>
Maintainer-email: Leo Guignard <leo.guignard@univ-amu.fr>
Project-URL: Bug Tracker, https://github.com/GuignardLab/moransi/issues
Project-URL: Documentation, https://github.com/GuignardLab/moransi#README.md
Project-URL: Source Code, https://github.com/GuignardLab/moransi
Project-URL: User Support, https://github.com/GuignardLab/moransi/issues
Classifier: Development Status :: 4 - Beta
Classifier: Intended Audience :: Developers
Classifier: Operating System :: OS Independent
Classifier: Programming Language :: Python
Classifier: Programming Language :: Python :: 3
Classifier: Programming Language :: Python :: 3 :: Only
Classifier: Programming Language :: Python :: 3.8
Classifier: Programming Language :: Python :: 3.9
Classifier: Programming Language :: Python :: 3.10
Classifier: Programming Language :: Python :: 3.11
Classifier: Programming Language :: Python :: 3.12
Classifier: Programming Language :: Python :: 3.13
Classifier: Programming Language :: Python :: 3.14
Requires-Python: >=3.8
License-File: LICENSE
Requires-Dist: numpy
Requires-Dist: scipy
Provides-Extra: dev
Requires-Dist: black[jupyter]; extra == "dev"
Requires-Dist: ruff; extra == "dev"
Requires-Dist: bumpver; extra == "dev"
Requires-Dist: pytest; extra == "dev"
Provides-Extra: test
Requires-Dist: pytest; extra == "test"
Requires-Dist: libpysal; extra == "test"
Dynamic: license-file
